<annotation>
	<folder>BCTC</folder>
	<filename>TN3_2_CDKT_108_1.jpg</filename>
	<path>D:\My Desktop\FINAL PROJECT\TABLE EXTRACTION\preprocess table\BCTC\TN3_2_CDKT_108_1.jpg</path>
	<source>
		<database>Unknown</database>
	</source>
	<size>
		<width>2480</width>
		<height>3509</height>
		<depth>3</depth>
	</size>
	<segmented>0</segmented>
	<object>
		<name>table</name>
		<pose>Unspecified</pose>
		<truncated>0</truncated>
		<difficult>0</difficult>
		<bndbox>
			<xmin>51</xmin>
			<ymin>461</ymin>
			<xmax>2330</xmax>
			<ymax>2332</ymax>
		</bndbox>
	</object>
<object>
		<name>table row</name>
		<pose>Unspecified</pose>
		<truncated>0</truncated>
		<difficult>0</difficult>
		<bndbox>
			<xmin>51</xmin>
			<ymin>507</ymin>
			<xmax>2330</xmax>
			<ymax>608</ymax>
		</bndbox>
	</object>
	<object>
		<name>table row</name>
		<pose>Unspecified</pose>
		<truncated>0</truncated>
		<difficult>0</difficult>
		<bndbox>
			<xmin>51</xmin>
			<ymin>629</ymin>
			<xmax>2330</xmax>
			<ymax>693</ymax>
		</bndbox>
	</object>
	<object>
		<name>table row</name>
		<pose>Unspecified</pose>
		<truncated>0</truncated>
		<difficult>0</difficult>
		<bndbox>
			<xmin>51</xmin>
			<ymin>717</ymin>
			<xmax>2330</xmax>
			<ymax>776</ymax>
		</bndbox>
	</object>
	<object>
		<name>table row</name>
		<pose>Unspecified</pose>
		<truncated>0</truncated>
		<difficult>0</difficult>
		<bndbox>
			<xmin>51</xmin>
			<ymin>788</ymin>
			<xmax>2330</xmax>
			<ymax>845</ymax>
		</bndbox>
	</object>
	<object>
		<name>table row</name>
		<pose>Unspecified</pose>
		<truncated>0</truncated>
		<difficult>0</difficult>
		<bndbox>
			<xmin>51</xmin>
			<ymin>848</ymin>
			<xmax>2330</xmax>
			<ymax>904</ymax>
		</bndbox>
	</object>
	<object>
		<name>table row</name>
		<pose>Unspecified</pose>
		<truncated>0</truncated>
		<difficult>0</difficult>
		<bndbox>
			<xmin>51</xmin>
			<ymin>908</ymin>
			<xmax>2330</xmax>
			<ymax>965</ymax>
		</bndbox>
	</object>
	<object>
		<name>table row</name>
		<pose>Unspecified</pose>
		<truncated>0</truncated>
		<difficult>0</difficult>
		<bndbox>
			<xmin>51</xmin>
			<ymin>980</ymin>
			<xmax>2330</xmax>
			<ymax>1035</ymax>
		</bndbox>
	</object>
	<object>
		<name>table row</name>
		<pose>Unspecified</pose>
		<truncated>0</truncated>
		<difficult>0</difficult>
		<bndbox>
			<xmin>51</xmin>
			<ymin>1039</ymin>
			<xmax>2330</xmax>
			<ymax>1086</ymax>
		</bndbox>
	</object>
	<object>
		<name>table row</name>
		<pose>Unspecified</pose>
		<truncated>0</truncated>
		<difficult>0</difficult>
		<bndbox>
			<xmin>51</xmin>
			<ymin>1089</ymin>
			<xmax>2330</xmax>
			<ymax>1142</ymax>
		</bndbox>
	</object>
	<object>
		<name>table row</name>
		<pose>Unspecified</pose>
		<truncated>0</truncated>
		<difficult>0</difficult>
		<bndbox>
			<xmin>51</xmin>
			<ymin>1156</ymin>
			<xmax>2330</xmax>
			<ymax>1208</ymax>
		</bndbox>
	</object>
	<object>
		<name>table row</name>
		<pose>Unspecified</pose>
		<truncated>0</truncated>
		<difficult>0</difficult>
		<bndbox>
			<xmin>51</xmin>
			<ymin>1221</ymin>
			<xmax>2330</xmax>
			<ymax>1284</ymax>
		</bndbox>
	</object>
	<object>
		<name>table row</name>
		<pose>Unspecified</pose>
		<truncated>0</truncated>
		<difficult>0</difficult>
		<bndbox>
			<xmin>51</xmin>
			<ymin>1285</ymin>
			<xmax>2330</xmax>
			<ymax>1339</ymax>
		</bndbox>
	</object>
	<object>
		<name>table row</name>
		<pose>Unspecified</pose>
		<truncated>0</truncated>
		<difficult>0</difficult>
		<bndbox>
			<xmin>51</xmin>
			<ymin>1340</ymin>
			<xmax>2330</xmax>
			<ymax>1395</ymax>
		</bndbox>
	</object>
	<object>
		<name>table row</name>
		<pose>Unspecified</pose>
		<truncated>0</truncated>
		<difficult>0</difficult>
		<bndbox>
			<xmin>51</xmin>
			<ymin>1395</ymin>
			<xmax>2330</xmax>
			<ymax>1498</ymax>
		</bndbox>
	</object>
	<object>
		<name>table row</name>
		<pose>Unspecified</pose>
		<truncated>0</truncated>
		<difficult>0</difficult>
		<bndbox>
			<xmin>51</xmin>
			<ymin>1501</ymin>
			<xmax>2330</xmax>
			<ymax>1561</ymax>
		</bndbox>
	</object>
	<object>
		<name>table row</name>
		<pose>Unspecified</pose>
		<truncated>0</truncated>
		<difficult>0</difficult>
		<bndbox>
			<xmin>51</xmin>
			<ymin>1563</ymin>
			<xmax>2330</xmax>
			<ymax>1617</ymax>
		</bndbox>
	</object>
	<object>
		<name>table row</name>
		<pose>Unspecified</pose>
		<truncated>0</truncated>
		<difficult>0</difficult>
		<bndbox>
			<xmin>51</xmin>
			<ymin>1624</ymin>
			<xmax>2330</xmax>
			<ymax>1677</ymax>
		</bndbox>
	</object>
	<object>
		<name>table row</name>
		<pose>Unspecified</pose>
		<truncated>0</truncated>
		<difficult>0</difficult>
		<bndbox>
			<xmin>51</xmin>
			<ymin>1679</ymin>
			<xmax>2330</xmax>
			<ymax>1736</ymax>
		</bndbox>
	</object>
	<object>
		<name>table row</name>
		<pose>Unspecified</pose>
		<truncated>0</truncated>
		<difficult>0</difficult>
		<bndbox>
			<xmin>51</xmin>
			<ymin>1740</ymin>
			<xmax>2330</xmax>
			<ymax>1802</ymax>
		</bndbox>
	</object>
	<object>
		<name>table row</name>
		<pose>Unspecified</pose>
		<truncated>0</truncated>
		<difficult>0</difficult>
		<bndbox>
			<xmin>51</xmin>
			<ymin>1813</ymin>
			<xmax>2330</xmax>
			<ymax>1871</ymax>
		</bndbox>
	</object>
	<object>
		<name>table row</name>
		<pose>Unspecified</pose>
		<truncated>0</truncated>
		<difficult>0</difficult>
		<bndbox>
			<xmin>51</xmin>
			<ymin>1876</ymin>
			<xmax>2330</xmax>
			<ymax>1930</ymax>
		</bndbox>
	</object>
	<object>
		<name>table row</name>
		<pose>Unspecified</pose>
		<truncated>0</truncated>
		<difficult>0</difficult>
		<bndbox>
			<xmin>51</xmin>
			<ymin>1938</ymin>
			<xmax>2330</xmax>
			<ymax>1997</ymax>
		</bndbox>
	</object>
	<object>
		<name>table row</name>
		<pose>Unspecified</pose>
		<truncated>0</truncated>
		<difficult>0</difficult>
		<bndbox>
			<xmin>51</xmin>
			<ymin>2014</ymin>
			<xmax>2330</xmax>
			<ymax>2072</ymax>
		</bndbox>
	</object>
	<object>
		<name>table row</name>
		<pose>Unspecified</pose>
		<truncated>0</truncated>
		<difficult>0</difficult>
		<bndbox>
			<xmin>51</xmin>
			<ymin>2075</ymin>
			<xmax>2330</xmax>
			<ymax>2127</ymax>
		</bndbox>
	</object>
	<object>
		<name>table row</name>
		<pose>Unspecified</pose>
		<truncated>0</truncated>
		<difficult>0</difficult>
		<bndbox>
			<xmin>51</xmin>
			<ymin>2128</ymin>
			<xmax>2330</xmax>
			<ymax>2187</ymax>
		</bndbox>
	</object>
	<object>
		<name>table row</name>
		<pose>Unspecified</pose>
		<truncated>0</truncated>
		<difficult>0</difficult>
		<bndbox>
			<xmin>51</xmin>
			<ymin>2189</ymin>
			<xmax>2330</xmax>
			<ymax>2243</ymax>
		</bndbox>
	</object>
	<object>
		<name>table row</name>
		<pose>Unspecified</pose>
		<truncated>0</truncated>
		<difficult>0</difficult>
		<bndbox>
			<xmin>51</xmin>
			<ymin>2246</ymin>
			<xmax>2330</xmax>
			<ymax>2298</ymax>
		</bndbox>
	</object>
	<object>
		<name>table column</name>
		<pose>Unspecified</pose>
		<truncated>0</truncated>
		<difficult>0</difficult>
		<bndbox>
			<xmin>79</xmin>
			<ymin>461</ymin>
			<xmax>1030</xmax>
			<ymax>2332</ymax>
		</bndbox>
	</object>
	<object>
		<name>table column</name>
		<pose>Unspecified</pose>
		<truncated>0</truncated>
		<difficult>0</difficult>
		<bndbox>
			<xmin>1142</xmin>
			<ymin>461</ymin>
			<xmax>1250</xmax>
			<ymax>2332</ymax>
		</bndbox>
	</object>
	<object>
		<name>table column</name>
		<pose>Unspecified</pose>
		<truncated>0</truncated>
		<difficult>0</difficult>
		<bndbox>
			<xmin>1266</xmin>
			<ymin>461</ymin>
			<xmax>1392</xmax>
			<ymax>2332</ymax>
		</bndbox>
	</object>
	<object>
		<name>table column</name>
		<pose>Unspecified</pose>
		<truncated>0</truncated>
		<difficult>0</difficult>
		<bndbox>
			<xmin>1451</xmin>
			<ymin>461</ymin>
			<xmax>1844</xmax>
			<ymax>2332</ymax>
		</bndbox>
	</object>
	<object>
		<name>table column</name>
		<pose>Unspecified</pose>
		<truncated>0</truncated>
		<difficult>0</difficult>
		<bndbox>
			<xmin>1909</xmin>
			<ymin>461</ymin>
			<xmax>2302</xmax>
			<ymax>2332</ymax>
		</bndbox>
	</object>
	<object>
		<name>table column header</name>
		<pose>Unspecified</pose>
		<truncated>0</truncated>
		<difficult>0</difficult>
		<bndbox>
			<xmin>51</xmin>
			<ymin>482</ymin>
			<xmax>2330</xmax>
			<ymax>626</ymax>
		</bndbox>
	</object>
</annotation>